talisman_domain-0.4.10.data/data/VERSION
tie_domain/__init__.py
tie_domain/configuration.py
tie_domain/domain/__init__.py
tie_domain/domain/producer.py
tie_domain/domain/_synthetic/__init__.py
tie_domain/domain/_synthetic/_category.py
tie_domain/domain/_synthetic/_common.py
tie_domain/domain/_synthetic/_platform.py
tie_domain/domain/_types/__init__.py
tie_domain/domain/_types/_abstract.py
tie_domain/domain/_types/_cached.py
tie_domain/domain/_types/_component.py
tie_domain/domain/_types/_nerc.py
tie_domain/domain/_types/_property.py
tie_domain/domain/_types/_relation.py
tie_domain/domain/_types/_relext.py
tie_domain/domain/_types/_value.py
tie_domain/domain/api/__init__.py
tie_domain/domain/api/api.py
tie_domain/domain/api/_impl/_0_14_10.py
tie_domain/domain/api/_impl/_0_14_8.py
tie_domain/domain/api/_impl/_0_16_4.py
tie_domain/domain/api/_impl/_0_17_0.py
tie_domain/domain/api/_impl/_0_17_3.py
tie_domain/domain/api/_impl/__init__.py
tie_domain/domain/api/_impl/_abstract.py
tie_domain/domain/api/_impl/graphql/0.14.10/kbutils.graphql
tie_domain/domain/api/_impl/graphql/0.14.8/kbutils.graphql
tie_domain/domain/api/_impl/graphql/0.16.4/kbutils.graphql
tie_domain/domain/api/_impl/graphql/0.17.0/kbutils.graphql
tie_domain/domain/api/_impl/graphql/0.17.3/kbutils.graphql
tie_domain/domain/updates_manager/__init__.py
tie_domain/domain/updates_manager/_abstract.py
tie_domain/domain/updates_manager/_ask.py
tie_domain/domain/updates_manager/_configuration.py
tie_domain/domain/updates_manager/_never.py
tie_domain/domain/updates_manager/_timeout.py
talisman_domain-0.4.10.dist-info/METADATA
talisman_domain-0.4.10.dist-info/WHEEL
talisman_domain-0.4.10.dist-info/entry_points.txt
talisman_domain-0.4.10.dist-info/top_level.txt
talisman_domain-0.4.10.dist-info/RECORD
