Metadata-Version: 2.4
Name: talisman-domain
Version: 0.4.10
Summary: Talisman domain implementations
Author: ISPRAS Talisman NLP team
Author-email: modis@ispras.ru
Maintainer: Vladimir Mayorov
Maintainer-email: vmayorov@ispras.ru
License: Apache Software License
Classifier: Development Status :: 3 - Alpha
Classifier: Programming Language :: Python :: 3
Classifier: Programming Language :: Python :: 3.11
Classifier: Intended Audience :: Developers
Classifier: Operating System :: OS Independent
Classifier: License :: OSI Approved :: Apache Software License
Requires-Python: >=3.10
Requires-Dist: talisman-interfaces<0.12,>=0.11.10
Requires-Dist: talisman-api~=1.3
Requires-Dist: talisman-dm<2,>=1.3.1
Requires-Dist: typing_extensions>=4.0.0
Dynamic: author
Dynamic: author-email
Dynamic: classifier
Dynamic: description-content-type
Dynamic: license
Dynamic: maintainer
Dynamic: maintainer-email
Dynamic: requires-dist
Dynamic: requires-python
Dynamic: summary
